ResPusher/__init__.py
ResPusher/respusher.py
ResPusher/serverchan.py
ResPusher/wxpusher.py
ResPusher-0.1.0.dist-info/LICENSE
ResPusher-0.1.0.dist-info/METADATA
ResPusher-0.1.0.dist-info/WHEEL
ResPusher-0.1.0.dist-info/top_level.txt
ResPusher-0.1.0.dist-info/RECORD
