Metadata-Version: 2.1
Name: ResPusher
Version: 0.1.0
Summary: 通过微信发送自己实验的结果
Home-page: https://github.com/XLJZT/ResPusher
Author: XLJZT
Author-email: xljzts@163.com
Classifier: Programming Language :: Python :: 3
Classifier: License :: OSI Approved :: MIT License
Classifier: Operating System :: OS Independent
Requires-Python: >=3.6
License-File: LICENSE
Requires-Dist: requests
